{
  "project_info": {
    "project_number": "1034929845680",
    "project_id": "rentit-78cc7",
    "storage_bucket": "rentit-78cc7.firebasestorage.app"
  },
  "client": [
    {
      "client_info": {
        "mobilesdk_app_id": "1:1034929845680:android:c782ab8337b5c38d4ed275",
        "android_client_info": {
          "package_name": "com.idz.rentIt"
        }
      },
      "oauth_client": [],
      "api_key": [
        {
          "current_key": "AIzaSyCAwvAZVYpX_9E7Sbmzi7LL_sUdG0m9EQc"
        }
      ],
      "services": {
        "appinvite_service": {
          "other_platform_oauth_client": []
        }
      }
    }
  ],
  "configuration_version": "1"
}